<dicti>
<H1><dentry>Pakk</dentry><dentryws></dentryws><Gram>BvA*para*&lt;Pakkawi&gt;,&lt;Pakkiwa&gt;</Gram><hmean no="1">SanEH-SanEH calanA-PiranA,PurwI se jAnA,sarakanA,XIre-XIre calanA</hmean><hgram></hgram><ref></ref><extra></extra><dentryws></dentryws><hmean no="2">galawI karanA,xurvyavahAra karanA</hmean><hgram></hgram><ref></ref><extra></extra><dentryws></dentryws><hmean no="3">PUla uTanA</hmean><hgram></hgram><ref></ref><extra></extra></H1>
<H1><dentry>PakkikA</dentry><dentryws></dentryws><Gram>swrI*</Gram><hmean no="1">eka avasWA,sixXa karane ke lie pUrvapakRa,ukwi yA prawijFA jisako banAye raKanA hE</hmean><hgram></hgram><ref>PaNiBARiwaBARyaPakkikA viRamA kUNdalanAmavApiwA nE* 2/95.</ref><extra></extra><dentryws></dentryws><hmean no="2">pakRapAwa,pUrvacinwiwa sammawi</hmean><hgram></hgram><ref></ref><extra></extra></H1>
<H1><dentry>Pat</dentry><dentryws></dentryws><Gram>avya*</Gram><hmean no="1">eka anukaraNamUlaka Sabxa jise jAxU maMwrAxika ke uccAraNa karane meM rahasyamaya rIwi se prayukwa kiyA jAwA hE-aswrAya Pat</hmean><hgram></hgram><ref></ref><extra>?PatAM? BI isI arWa meM , pATAnwara-PaNA</extra></H1>
<H1><dentry>PataH</dentry><dentryws></dentryws><Gram>puM*</Gram><hmean no="1">sAzpa kA prasAriwa kiyA huA PaNA</hmean><hgram></hgram><ref>nirviReNApi sarpeNa karwavyA mahawI PatA viRaM Bavawu mA BUxvA PatAtopo BayafkaraHpaMca* 1/204</ref><extra></extra><dentryws></dentryws><hmean no="2">xAzwa</hmean><hgram></hgram><ref></ref><extra></extra><dentryws></dentryws><hmean no="3">XUrwa,Taga,kiwava</hmean><hgram></hgram><ref></ref><extra></extra></H1>
<H1><dentry>PadigA</dentry><dentryws></dentryws><Gram>swrI*</Gram><hmean no="1">JIMgura,tiddI,tiddA,PawiMgA</hmean><hgram></hgram><ref></ref><extra></extra></H1>
<H1><dentry>PaN</dentry><dentryws></dentryws><Gram>BvA*para*&lt;PaNawi&gt;,&lt;PaNiwa&gt;</Gram><hmean no="1">calanA-PiranA,iXara-uXara GUmanA</hmean><hgram></hgram><ref>rurujurBejire PeNurbahuXAharirAkRasAHBatti* 14/78</ref><extra>yaha arWa kuCa ke mawAnusAra preraNArWaka kriyA kA hE</extra><dentryws></dentryws><hmean no="2">anAyAsa uwpanna karanA,binA kisI pariSrama ke pExA karanA</hmean><hgram></hgram><ref></ref><extra></extra></H1>
<H1><dentry>PaNaH</dentry><dentryws></dentryws><Gram>swrI*</Gram><hmean no="1">kisI BI sAzpa kA PElAyA huA PaNa</hmean><hgram></hgram><ref>viprakqwaH pannaga PaNaM(PaNAM) kuruweSa* 6/30,maNiBiH PaNasWEHraGu* 13/12,ku* 6/68,vahawi BuvanaSreNi SeRaH PaNAPalakasWiwAmBarwq* 2/35</ref><extra></extra></H1>
<H1><dentry>PaNA</dentry><dentryws></dentryws><Gram>swrI*</Gram><hmean no="1">kisI BI sAzpa kA PElAyA huA PaNa</hmean><hgram></hgram><ref>viprakqwaH pannaga PaNaM(PaNAM) kuruweSa* 6/30,maNiBiH PaNasWEHraGu* 13/12,ku* 6/68,vahawi BuvanaSreNi SeRaH PaNAPalakasWiwAmBarwq* 2/35</ref><extra></extra>
<H2 entry="1"><dentry>PaNakaraH</dentry><dentryws></dentryws><Gram>puM*</Gram><hmean no="1">sAzpa</hmean><gender></gender><ref></ref><extra></extra></H2>
<H2 entry="2"><dentry>PaNaXaraH</dentry><dentryws></dentryws><Gram>puM*</Gram><hmean no="1">sAzpa</hmean><gender></gender><ref></ref><extra></extra><dentryws></dentryws><hmean no="2">Siva kA nAma</hmean><gender></gender><ref></ref><extra></extra></H2>
<H2 entry="4"><dentry>PaNaBqw</dentry><dentryws></dentryws><Gram>puM*</Gram><hmean no="1">sAzpa</hmean><gender></gender><ref></ref><extra></extra></H2>
<H2 entry="5"><dentry>PaNamaNiH</dentry><dentryws></dentryws><Gram>puM*</Gram><hmean no="1">sAzpa ke PaNa meM pAI jAne vAlI maNi</hmean><gender></gender><ref></ref><extra></extra></H2>
<H2 entry="6"><dentry>PaNamaNdalam</dentry><dentryws></dentryws><Gram>napuM*</Gram><hmean no="1">sAzpa kA kuMdalIkqwa SarIra</hmean><gender></gender><ref>karAlaPalamaNdala  raGu*12/18,wawPaNAmaNdaloxarcirmaNixyowiwavigraham10/7</ref><extra></extra></H2>
</H1>
<H1><dentry>PaNin</dentry><dentryws></dentryws><Gram>puM*</Gram><hmean no="1">PaNaXArI sAzpa,sAmAnya sAzpa,sarpa</hmean><hgram></hgram><ref>uxgirawo yaxgaralaM PaNinaH puRNAsi parimaloxgArEH   BAgi* 1/12,58,PaNI mayUrasya wale niRIxawi  qwu* 1/13,raGu* 16/17,ku* 3/21</ref><extra></extra><dentryws></dentryws><hmean no="2">rAhu kA viSeRaNa</hmean><hgram></hgram><ref></ref><extra></extra><dentryws></dentryws><hmean no="3">pawaMjali kA viSeRaNa</hmean><hgram></hgram><ref>PaNi  BARiwaBARyaPakkikA  nE* 2/95</ref><extra>pANinI ke sUwroM para mahABARya ke praNewA</extra>
<H2 entry="1"><dentry>PaNInxraH</dentry><dentryws></dentryws><Gram>puM*</Gram><hmean no="1">SeRanAga kA viSeRaNa</hmean><gender></gender><ref></ref><extra></extra><dentryws></dentryws><hmean no="2">sAzpoM ke aXipawi ananwa kA viSeRaNa</hmean><gender></gender><ref></ref><extra></extra><dentryws></dentryws><hmean no="3">pawaMjali kA viSeRaNa</hmean><gender></gender><ref></ref><extra></extra></H2>
<H2 entry="4"><dentry>PaNISvaraH</dentry><dentryws></dentryws><Gram>puM*</Gram><hmean no="1">SeRanAga kA viSeRaNa</hmean><gender></gender><ref></ref><extra></extra><dentryws></dentryws><hmean no="2">sAzpoM ke aXipawi ananwa kA viSeRaNa</hmean><gender></gender><ref></ref><extra></extra><dentryws></dentryws><hmean no="3">pawaMjali kA viSeRaNa</hmean><gender></gender><ref></ref><extra></extra></H2>
<H2 entry="7"><dentry>PaNiKelaH</dentry><dentryws></dentryws><Gram>puM*</Gram><hmean no="1">lavA,batera</hmean><gender></gender><ref></ref><extra></extra></H2>
<H2 entry="8"><dentry>PaNiwalpagaH</dentry><dentryws></dentryws><Gram>puM*</Gram><hmean no="1">viRNu kA viSeRaNa</hmean><gender></gender><ref></ref><extra>SeRanAga jinakI SayyA hE</extra></H2>
<H2 entry="9"><dentry>PaNipawiH</dentry><dentryws></dentryws><Gram>puM*</Gram><hmean no="1">vAsuki yA SeRanAga kA viSeRaNa</hmean><gender></gender><ref></ref><extra></extra><dentryws></dentryws><hmean no="2">pawaMjali kA viSeRaNa</hmean><gender></gender><ref></ref><extra></extra></H2>
<H2 entry="11"><dentry>PaNipriyaH</dentry><dentryws></dentryws><Gram>puM*</Gram><hmean no="1">vAyu</hmean><gender></gender><ref></ref><extra></extra></H2>
<H2 entry="12"><dentry>PaNiPenaH</dentry><dentryws></dentryws><Gram>puM*</Gram><hmean no="1">aPIma</hmean><gender></gender><ref></ref><extra></extra></H2>
<H2 entry="13"><dentry>PaNiBARyam</dentry><dentryws></dentryws><Gram>napuM*</Gram><hmean no="1">mahABARya</hmean><gender></gender><ref></ref><extra>pANini ke sUwroM para kiyA gayA BARya</extra></H2>
<H2 entry="14"><dentry>PaNiBuj</dentry><dentryws></dentryws><Gram>puM*</Gram><hmean no="1">mora</hmean><gender></gender><ref></ref><extra></extra><dentryws></dentryws><hmean no="2">garuNa kA viSeRaNa</hmean><gender></gender><ref></ref><extra></extra></H2>
</H1>
<H1><dentry>PawkArin</dentry><dentryws></dentryws><Gram>puM*</Gram><hmean no="1">pakRI</hmean><hgram></hgram><ref></ref><extra></extra></H1>
<H1><dentry>Param</dentry><dentryws></dentryws><Gram>napuM*</Gram><hmean no="1">Palaka</hmean><hgram></hgram><ref>DAla  wu*</ref><extra></extra></H1>
<H1><dentry>Parubakam</dentry><dentryws></dentryws><Gram>napuM*</Gram><hmean no="1">pAnaxAna pAna raKane kA dabbA</hmean><hgram></hgram><ref></ref><extra></extra></H1>
<H1><dentry>ParParIkaH</dentry><dentryws></dentryws><Gram>puM*</Gram><hmean no="1">Kule hue hAWa kI haWelI</hmean><hgram></hgram><ref></ref><extra></extra></H1>
<H1><dentry>ParParIkam</dentry><dentryws></dentryws><Gram>napuM*</Gram><hmean no="1">wAjA aMkura yA tahanI kA aMKuvA</hmean><hgram></hgram><ref></ref><extra></extra><dentryws></dentryws><hmean no="2">mqxuwA</hmean><hgram></hgram><ref></ref><extra></extra></H1>
<H1><dentry>ParParIkA</dentry><dentryws></dentryws><Gram>swrI*</Gram><hmean no="1">jUwA</hmean><hgram></hgram><ref></ref><extra></extra></H1>
<H1><dentry>Pal</dentry><dentryws></dentryws><Gram>BvA*para*&lt;Palawi&gt;,&lt;Paliwa&gt;</Gram><hmean no="1">Pala AnA,Pala pExA karanA ?niRpanna yA Gatiwa karanA?</hmean><hgram></hgram><ref>nAnAPalEH Palawi kalpalaweva vixyA  Barwq* 2/40,paropakArAya xrumAH Palanwi  suBA* viXAwurvyApAraH PalawuH ca manojFaSca Bavawu  mA* 1/16,mOryasyEva Palanwi viviXaSreyAMsi mannIwayaH  muxrA* 2/16</ref><extra>isa arWa meM prAyaH sakarmaka ke rupa me XAwu kA prayoga howA hE</extra><dentryws></dentryws><hmean no="2">pariNAmayukwa honA,saPala honA,pUrA honA,niRpanna honA,kAmayAba honA</hmean><hgram></hgram><ref>kEkeyi kAmAH PaliwAswavewi  raGu* 13/59,15/78,yaxA na PeluH kRaNaxAcarANAM  Batti* 14/113,12/66,nEvAkqwiH Palawi nEva kulaM na SIlam  Barwq* 2/96/116</ref><extra>manoraWAH</extra><dentryws></dentryws><hmean no="3">Pala nikalanA,pariNAma yA nawIjA pExA karanA,?xuRta vyakwi bure kArya karawe hEM Ora Bale puruRoM ko unakA pariNAma BugawanA padZawA hE</hmean><hgram></hgram><ref>PaliwamasmAkaM kapataprabanXena  hi* 1,PaliwaM naswarhi BagavawI pAxaprasAxena  mA* 6,ki* 18/25,KalaH karowi xurvqwwaM nUnaM Palawi sAXuRu  hi* 3/21</ref><extra></extra><dentryws></dentryws><hmean no="4">pakkA honA,paka jAnA</hmean><hgram></hgram><ref></ref><extra></extra><dentryws></dentryws><Gram>BvA*para*&lt;Palawi&gt;,&lt;Pulla yA Pulwa&gt;</Gram><hmean no="1">balapUrvaka wodZanA,KaMda-KaMda karanA,Pata jAnA,xarAra padZanA</hmean><hgram></hgram><ref>wasya mUrXAnamAsAxya paPAlAsivaro hi saH  mahA*</ref><extra></extra><dentryws></dentryws><hmean no="2">prawiPaliwa honA,aksa padZanA</hmean><hgram></hgram><ref>ki* 5/38</ref><extra></extra><dentryws></dentryws><hmean no="3">jAnA</hmean><hgram></hgram><ref></ref><extra></extra></H1>
<H1><dentry>Palam</dentry><dentryws></dentryws><Gram>napuM*</Gram><hmean no="1">Pala jEse vqkRa kA</hmean><hgram></hgram><ref>uxewi pUrvaM kusuma wawaH Palam  Sa* 7/30,raGu* 4/33,1/49</ref><extra>AlaM0se BI</extra><dentryws></dentryws><hmean no="2">Pasala,pExavAra</hmean><hgram></hgram><ref>kqRiPalaM  meGa*  16</ref><extra></extra><dentryws></dentryws><hmean no="3">pariNAma,Pala,nawIjA,praBAva</hmean><hgram></hgram><ref>awyuwkateH pApapuNyErihEva PalamaSnuwe   hi* 1/83,Palena jFAsyasi  paMca* 1,na navaH praBurAPaloxayAw sWirakarmA virarAma karmaNaH  raGu* 8/22,1/33</ref><extra></extra><dentryws></dentryws><hmean no="4">puraskAra,kRawipUrwi,pAriwoRaka prawiPala</hmean><hgram></hgram><ref>PalamasyopahAsasya saxyaH prApsyasi paSya mAm  raGu* 12/37</ref><extra>awaH , SuBa yA aSuBa</extra><dentryws></dentryws><hmean no="5">kqwya,karma? Bale puruRa apanI upayogiwA karmoM se sixXa karawe hE na ki vacanoM se?</hmean><hgram></hgram><ref>bruvawe hi Palena sAXavo na wu kaMTena nijopayogiwAm   nE* 2/48</ref><extra>vipa0 vacan</extra><dentryws></dentryws><hmean no="6">uxxeSya,ASaya,prayojana? kisa ASaya ko vicAra meM raKakara?</hmean><hgram></hgram><ref>parefgiwajFAnaPalA hi buxXayaH  paMca* 1/43,kimapekRya Palam  ki* 2/21,meGa* 54</ref><extra></extra><dentryws></dentryws><hmean no="7">upayoga,BalAI,lABa,hiwa</hmean><hgram></hgram><ref>jagawA vA viPalena kiM Palam  BAmi* 2/61</ref><extra></extra><dentryws></dentryws><hmean no="8">lABa yA mUlarASi kA byAja</hmean><hgram></hgram><ref></ref><extra></extra><dentryws></dentryws><hmean no="9">prajA,sanwAna</hmean><hgram></hgram><ref> raGu* 14/39</ref><extra></extra><dentryws></dentryws><hmean no="10">girI</hmean><hgram></hgram><ref></ref><extra>Pala kI</extra><dentryws></dentryws><hmean no="11">pattikA yA Palaka</hmean><hgram></hgram><ref></ref><extra></extra><dentryws></dentryws><hmean no="12">Pala</hmean><hgram></hgram><ref></ref><extra>walavAra kA</extra><dentryws></dentryws><hmean no="13">wIra kI noka yA sirA,bANa,gIwakAra</hmean><hgram></hgram><ref>  muxrA* 7/10</ref><extra></extra><dentryws></dentryws><hmean no="14">DAla</hmean><hgram></hgram><ref></ref><extra></extra><dentryws></dentryws><hmean no="15">aMdakoRa</hmean><hgram></hgram><ref></ref><extra></extra><dentryws></dentryws><hmean no="16">upahAra</hmean><hgram></hgram><ref></ref><extra></extra><dentryws></dentryws><hmean no="17">gaNanA Pala</hmean><hgram></hgram><ref></ref><extra>gaNiwa meM</extra><dentryws></dentryws><hmean no="18">guNanaPala</hmean><hgram></hgram><ref></ref><extra></extra><dentryws></dentryws><hmean no="19">rajaHswrAvaH</hmean><hgram></hgram><ref></ref><extra></extra><dentryws></dentryws><hmean no="20">jAyaPala</hmean><hgram></hgram><ref></ref><extra></extra><dentryws></dentryws><hmean no="21">hala kA Pala,PAlI</hmean><hgram></hgram><ref></ref><extra></extra>
<H2 entry="1"><dentry>PalAxanaH</dentry><dentryws></dentryws><Gram>puM*</Gram><hmean no="1">PalASana</hmean><gender></gender><ref></ref><extra></extra></H2>
<H2 entry="2"><dentry>PalAnubanXaH</dentry><dentryws></dentryws><Gram>puM*</Gram><hmean no="1">pariNAmakrama,PalaparamparA</hmean><gender></gender><ref></ref><extra></extra></H2>
<H2 entry="3"><dentry>PalAnumeya</dentry><dentryws></dentryws><Gram>vi*</Gram><hmean no="1">jisakA anumAna Pala yA pariNAma para nirBara ho</hmean><gender></gender><ref>PalAnumeyAH prAramBAH saMskArAH prAkwAnA iva  raGu* 1/20</ref><extra></extra></H2>
<H2 entry="4"><dentry>PalAnwaH</dentry><dentryws></dentryws><Gram>puM*</Gram><hmean no="1">bAMsa</hmean><gender></gender><ref></ref><extra></extra></H2>
<H2 entry="5"><dentry>PalAnveRin</dentry><dentryws></dentryws><Gram>vi*</Gram><hmean no="1">puraskAra yA kRawipUrwi kI Koja karane vAlA</hmean><gender></gender><ref></ref><extra>karmo ke</extra></H2>
<H2 entry="6"><dentry>PalApekRA</dentry><dentryws></dentryws><Gram>swrI*</Gram><hmean no="1">Pala yA pariNAmoM kI ASA,nawIje kA XyAna</hmean><gender></gender><ref></ref><extra>karmo ke</extra></H2>
<H2 entry="7"><dentry>PalASanaH</dentry><dentryws></dentryws><Gram>puM*</Gram><hmean no="1">wowA</hmean><gender></gender><ref></ref><extra></extra></H2>
<H2 entry="8"><dentry>PalAmlam</dentry><dentryws></dentryws><Gram>napuM*</Gram><hmean no="1">imalI</hmean><gender></gender><ref></ref><extra></extra></H2>
<H2 entry="9"><dentry>PalAsWi</dentry><dentryws></dentryws><Gram>napuM*</Gram><hmean no="1">nAriyala</hmean><gender></gender><ref></ref><extra></extra></H2>
<H2 entry="10"><dentry>PalAkAfkRA</dentry><dentryws></dentryws><Gram>swrI*</Gram><hmean no="1">ASA</hmean><gender></gender><ref></ref><extra>xe*  PalApekRA acCe pariNAmoM kI</extra></H2>
<H2 entry="11"><dentry>PalAgamaH</dentry><dentryws></dentryws><Gram>puM*</Gram><hmean no="1">PaloM kI pExavAra,PaloM kA BAra</hmean><gender></gender><ref>Bavanwi namrAswaravaH PalAgamEH  Sa* 5/12</ref><extra></extra><dentryws></dentryws><hmean no="2">PaloM kA mOsama,pawaJadZa</hmean><gender></gender><ref></ref><extra></extra></H2>
<H2 entry="13"><dentry>PalADya</dentry><dentryws></dentryws><Gram>vi*</Gram><hmean no="1">PaloM se BarA huyA</hmean><gender></gender><ref></ref><extra></extra><dentryws></dentryws><Gram>swrI*</Gram><hmean no="1">eka prakAra ke aMgura</hmean><gender></gender><ref></ref><extra>jisameM guTaliyAz yA bIja nahIM howe</extra></H2>
<H2 entry="15"><dentry>PalowpawwiH</dentry><dentryws></dentryws><Gram>swrI*</Gram><hmean no="1">PaloM kI pExavAra</hmean><gender></gender><ref></ref><extra></extra><dentryws></dentryws><hmean no="2">PAyaxA,lABa,Ama kA vqkRa</hmean><gender></gender><ref></ref><extra>kaBI-kaBI isI arWa ko prakata karane ke lie ?Palowpawi? BI liKA jAwA hE ,</extra></H2>
<H2 entry="17"><dentry>PaloxayaH</dentry><dentryws></dentryws><Gram>puM*</Gram><hmean no="1">PaloM kA xiKAI xenA,Pala yA pariNAma kA nikalanA,aBIRta paxArWa yA saPalawA kI prApwi</hmean><gender></gender><ref>APaloxayakarmaNAm  raGu* 1/5</ref><extra>AnA</extra></H2>
<H2 entry="18"><dentry>PaloxxeSaH</dentry><dentryws></dentryws><Gram>puM*</Gram><hmean no="1">PaloM kA XyAna</hmean><gender></gender><ref></ref><extra>xe0 PalApekRA</extra></H2>
<H2 entry="19"><dentry>PalakAmanA</dentry><dentryws></dentryws><Gram>swrI*</Gram><hmean no="1">pariNAma yA Pala kI icCA</hmean><gender></gender><ref></ref><extra></extra></H2>
<H2 entry="20"><dentry>PalakAlaH</dentry><dentryws></dentryws><Gram>puM*</Gram><hmean no="1">PaloM kA samaya</hmean><gender></gender><ref></ref><extra></extra></H2>
<H2 entry="21"><dentry>PalakeSaraH</dentry><dentryws></dentryws><Gram>puM*</Gram><hmean no="1">nAriyala kA pedZa</hmean><gender></gender><ref></ref><extra></extra></H2>
<H2 entry="22"><dentry>PalagrahaH+grahin</dentry><dentryws></dentryws><Gram>vi*</Gram><hmean no="1">PaloM se BarA huA,mOsama me Pala xene</hmean><gender></gender><ref>SlAGyawAM kulamupEwi pEwqkaM syAnmanoraWawaruH PalegrahiH  kIrwi* 3/60,mA* 9/39</ref><extra>Palegrahi yA PalegrAhin</extra></H2>
<H2 entry="23"><dentry>Palaxa</dentry><dentryws></dentryws><Gram>vi*</Gram><hmean no="1">upajAU,PalaxAra,Pala xene vAlA</hmean><gender></gender><ref> manu* 11/142</ref><extra></extra><dentryws></dentryws><hmean no="2">lABakara yA PAyaxA pahuMcAne vAlA</hmean><gender></gender><ref></ref><extra></extra></H2>
<H2 entry="25"><dentry>PalaxaH</dentry><dentryws></dentryws><Gram>puM*</Gram><hmean no="1">vqkRa</hmean><gender></gender><ref></ref><extra></extra></H2>
<H2 entry="26"><dentry>PalanivqwwiH</dentry><dentryws></dentryws><Gram>swrI*</Gram><hmean no="1">pariNAmoM kI samApwi</hmean><gender></gender><ref></ref><extra></extra></H2>
<H2 entry="27"><dentry>PalaniRpawwiH</dentry><dentryws></dentryws><Gram>swrI*</Gram><hmean no="1">PaloM kA uwpAxana</hmean><gender></gender><ref></ref><extra></extra></H2>
<H2 entry="28"><dentry>PalapAkaH</dentry><dentryws></dentryws><Gram>puM*</Gram><hmean no="1">PaloM kA pakanA</hmean><gender></gender><ref></ref><extra>PalepAkaH? BI</extra><dentryws></dentryws><hmean no="2">pariNAmoM kI pUrNawA</hmean><gender></gender><ref></ref><extra></extra></H2>
<H2 entry="30"><dentry>PalapAxapaH</dentry><dentryws></dentryws><Gram>puM*</Gram><hmean no="1">PalavqkRa</hmean><gender></gender><ref></ref><extra></extra></H2>
<H2 entry="31"><dentry>PalapUraH</dentry><dentryws></dentryws><Gram>puM*</Gram><hmean no="1">sAmAnya nIbU kA pedZ</hmean><gender></gender><ref></ref><extra></extra></H2>
<H2 entry="32"><dentry>PalapUrakaH</dentry><dentryws></dentryws><Gram>puM*</Gram><hmean no="1">sAmAnya nIbU kA pedZ</hmean><gender></gender><ref></ref><extra></extra></H2>
<H2 entry="33"><dentry>PalapraxAnam</dentry><dentryws></dentryws><Gram>napuM*</Gram><hmean no="1">PaloM kA xenA</hmean><gender></gender><ref></ref><extra></extra><dentryws></dentryws><hmean no="2">vivAha ke avasara para eka saMskAra viSeRa</hmean><gender></gender><ref></ref><extra></extra></H2>
<H2 entry="35"><dentry>PalabanXin</dentry><dentryws></dentryws><Gram>vi*</Gram><hmean no="1">Pala ko vikasiwa karane vAlA yA rupa xene vAlA</hmean><gender></gender><ref></ref><extra></extra></H2>
<H2 entry="36"><dentry>PalaBUmiH</dentry><dentryws></dentryws><Gram>swrI*</Gram><hmean no="1">vaha sWAna jahAz manuRya apane karmoM kA SuBASuBa Pala BogawA hE</hmean><gender></gender><ref></ref><extra>arWAw svarga yA naraka</extra></H2>
<H2 entry="37"><dentry>PalaBqw</dentry><dentryws></dentryws><Gram>vi*</Gram><hmean no="1">PalaxAyI,PaloM se pUrNa</hmean><gender></gender><ref></ref><extra></extra></H2>
<H2 entry="38"><dentry>PalaBogaH</dentry><dentryws></dentryws><Gram>puM*</Gram><hmean no="1">PaloM kA Ananxa lenA</hmean><gender></gender><ref></ref><extra></extra><dentryws></dentryws><hmean no="2">BogAXikAra</hmean><gender></gender><ref></ref><extra></extra></H2>
<H2 entry="40"><dentry>PalayogaH</dentry><dentryws></dentryws><Gram>puM*</Gram><hmean no="1">aBIRtapaxArWa yA Pala kI prApwi</hmean><gender></gender><ref> muxrA* 7/10</ref><extra></extra><dentryws></dentryws><hmean no="2">majaxUrI,pAriSramika</hmean><gender></gender><ref></ref><extra></extra></H2>
<H2 entry="42"><dentry>PalarAjan</dentry><dentryws></dentryws><Gram>puM*</Gram><hmean no="1">warabUjA</hmean><gender></gender><ref></ref><extra></extra></H2>
<H2 entry="43"><dentry>Palavawulam</dentry><dentryws></dentryws><Gram>napuM*</Gram><hmean no="1">warabUja</hmean><gender></gender><ref></ref><extra></extra></H2>
<H2 entry="44"><dentry>PalavqkRaH</dentry><dentryws></dentryws><Gram>puM*</Gram><hmean no="1">PalaxAravqkRa</hmean><gender></gender><ref></ref><extra></extra></H2>
<H2 entry="45"><dentry>PalavqkRaka</dentry><dentryws></dentryws><Gram>puM*</Gram><hmean no="1">katahala kA vqkRa</hmean><gender></gender><ref></ref><extra></extra></H2>
<H2 entry="46"><dentry>PalaSAdavaH</dentry><dentryws></dentryws><Gram>puM*</Gram><hmean no="1">anAra kA pedZa</hmean><gender></gender><ref></ref><extra></extra></H2>
<H2 entry="47"><dentry>PalaSreRTaH</dentry><dentryws></dentryws><Gram>puM*</Gram><hmean no="1">Ama kA pedZa</hmean><gender></gender><ref></ref><extra></extra></H2>
<H2 entry="48"><dentry>Palasampax</dentry><dentryws></dentryws><Gram>swrI*</Gram><hmean no="1">PaloM kI bahuwAyawa</hmean><gender></gender><ref></ref><extra></extra><dentryws></dentryws><hmean no="2">saPalawA</hmean><gender></gender><ref></ref><extra></extra></H2>
<H2 entry="50"><dentry>PalasAXanam</dentry><dentryws></dentryws><Gram>napuM*</Gram><hmean no="1">aBIRta paxArWa kI upalabXi kA upAya,uxxeSya kI pUrwi</hmean><gender></gender><ref></ref><extra></extra></H2>
<H2 entry="51"><dentry>PalasnehaH</dentry><dentryws></dentryws><Gram>puM*</Gram><hmean no="1">aKarota kA pedZa</hmean><gender></gender><ref></ref><extra></extra></H2>
<H2 entry="52"><dentry>PalahArI</dentry><dentryws></dentryws><Gram>swrI*</Gram><hmean no="1">kAlI yA xurgA kA viSeRaNa</hmean><gender></gender><ref></ref><extra></extra></H2>
</H1>
<H1><dentry>Palakam</dentry><dentryws></dentryws><Gram>napuM*</Gram><hmean no="1">patta,waKwA,SilA,patala yA pattI</hmean><hgram></hgram><ref>kAlaH kAlyA BuvanaPalake krIdawi prANiSArEH  Barwq* 3/39,xyUwa*ciwra* Axi</ref><extra></extra><dentryws></dentryws><hmean no="2">capatI sawaha</hmean><hgram></hgram><ref>cuMbyamAnakapola PalakAm  kA* 218,XqwamugXagaMNdaPalakErvibaBuH  Si* 9/47,37,wu* ?wata?</ref><extra></extra><dentryws></dentryws><hmean no="3">DAla</hmean><hgram></hgram><ref></ref><extra></extra><dentryws></dentryws><hmean no="4">pawra pqRTa</hmean><hgram></hgram><ref></ref><extra></extra><dentryws></dentryws><hmean no="5">niwaMba,kUlhA</hmean><hgram></hgram><ref></ref><extra></extra><dentryws></dentryws><hmean no="6">hAWa kI haWelI</hmean><hgram></hgram><ref></ref><extra></extra>
<H2 entry="1"><dentry>PalakapANi</dentry><dentryws></dentryws><Gram>vi*</Gram><hmean no="1">DAla se susajjiwa</hmean><gender></gender><ref></ref><extra>yoxXA kI BAMwi</extra></H2>
<H2 entry="2"><dentry>Palakayanwram</dentry><dentryws></dentryws><Gram>napuM*</Gram><hmean no="1">BAskarAcArya xvArA AviRkqwa eka jyowirviRayaka upakaraNa</hmean><gender></gender><ref></ref><extra></extra></H2>
</H1>
<H1><dentry>PalawaH</dentry><dentryws></dentryws><Gram>avya*</Gram><hmean no="1">Palasvarupa,pariNAmarupa,yaWArWawaH</hmean><hgram></hgram><ref></ref><extra></extra></H1>
<H1><dentry>Palanam</dentry><dentryws></dentryws><Gram>napuM*</Gram><hmean no="1">Pala AnA,PalavAn honA</hmean><hgram></hgram><ref></ref><extra></extra><dentryws></dentryws><hmean no="2">Pala yA pariNAma uwpanna karanA</hmean><hgram></hgram><ref></ref><extra></extra></H1>
<H1><dentry>Palavaw</dentry><dentryws></dentryws><Gram>vi*</Gram><hmean no="1">PalavAna,PalaxAra</hmean><hgram></hgram><ref></ref><extra></extra><dentryws></dentryws><hmean no="2">PalaxAyI,pariNAmaxarSI saPala,lABakArI</hmean><hgram></hgram><ref></ref><extra></extra></H1>
<H1><dentry>PalavawI</dentry><dentryws></dentryws><Gram>swrI*</Gram><hmean no="1">?priyaMgu? nAmaka lawA</hmean><hgram></hgram><ref></ref><extra></extra></H1>
<H1><dentry>PaliwA</dentry><dentryws></dentryws><Gram>swrI*</Gram><hmean no="1">rajasvalA swrI</hmean><hgram></hgram><ref></ref><extra></extra></H1>
<H1><dentry>Palin</dentry><dentryws></dentryws><Gram>vi*</Gram><hmean no="1">PaloM se pUrNa,PalaxAyI</hmean><hgram></hgram><ref>puRpiNaH PalinaScEva vqkRAswUBayawaH smqwAH  manu* 1/47,mqcCa* 4/10</ref><extra></extra><dentryws></dentryws><Gram>puM*</Gram><hmean no="1">vqkRa</hmean><hgram></hgram><ref>puRpiNaH PalinaScEva vqkRAswUBayawaH smqwAH  manu* 1/47,mqcCa* 4/10</ref><extra></extra></H1>
<H1><dentry>Palina</dentry><dentryws></dentryws><Gram>vi*</Gram><hmean no="1">PaloM se pUrNa,PalaxAyI</hmean><hgram></hgram><ref></ref><extra></extra></H1>
<H1><dentry>PalinaH</dentry><dentryws></dentryws><Gram>puM*</Gram><hmean no="1">katahala kA pedZa</hmean><hgram></hgram><ref></ref><extra></extra></H1>
<H1><dentry>PalinI</dentry><dentryws></dentryws><Gram>swrI*</Gram><hmean no="1">priyaMgu lawA</hmean><hgram></hgram><ref> wu* raGU* 8/61</ref><extra>kaviyoM ke xvArA ise?Ama kI pawnI? kahA gayA hE</extra></H1>
<H1><dentry>PalInI</dentry><dentryws></dentryws><Gram>swrI*</Gram><hmean no="1">priyaMgu lawA</hmean><hgram></hgram><ref> wu* raGU* 8/61</ref><extra>kaviyoM ke xvArA ise?Ama kI pawnI? kahA gayA hE</extra></H1>
<H1><dentry>Palgu</dentry><dentryws></dentryws><Gram>vi*</Gram><hmean no="1">binA gUxe kA,rasahIna,wawvarahiwa,sAravihIna</hmean><hgram></hgram><ref>sAraM wawo grAhyamapAsya Palgu  paMca* 1/2</ref><extra></extra><dentryws></dentryws><hmean no="2">ayogya,nirarWaka,mahawvahIna</hmean><hgram></hgram><ref> Si* 3/76</ref><extra></extra><dentryws></dentryws><hmean no="3">alpa,sukRm</hmean><hgram></hgram><ref></ref><extra></extra><dentryws></dentryws><hmean no="4">nirmUla,vyarWa</hmean><hgram></hgram><ref></ref><extra></extra><dentryws></dentryws><hmean no="5">xurbala,balahIna,nissAra</hmean><hgram></hgram><ref></ref><extra></extra></H1>
<H1><dentry>PalguH</dentry><dentryws></dentryws><Gram>swrI*</Gram><hmean no="1">vasanwaqwu</hmean><hgram></hgram><ref></ref><extra></extra><dentryws></dentryws><Gram>puM*</Gram><hmean no="1">gUlara kA vqkRa</hmean><hgram></hgram><ref></ref><extra></extra><dentryws></dentryws><hmean no="2">gayA ke pAsa eka naxI</hmean><hgram></hgram><ref></ref><extra></extra>
<H2 entry="1"><dentry>PalgUwsavaH</dentry><dentryws></dentryws><Gram>puM*</Gram><hmean no="1">vasanwowsava,holI kA wyohAra</hmean><gender></gender><ref></ref><extra></extra></H2>
</H1>
<H1><dentry>PalgunaH</dentry><dentryws></dentryws><Gram>puM*</Gram><hmean no="1">PAlguna kA mahInA</hmean><hgram></hgram><ref></ref><extra></extra><dentryws></dentryws><hmean no="2">inxra kA nAmAnwara</hmean><hgram></hgram><ref></ref><extra></extra></H1>
<H1><dentry>PAlgunI</dentry><dentryws></dentryws><Gram>swrI*</Gram><hmean no="1">eka nakRawra kA nAma</hmean><hgram></hgram><ref> ku* 7/6</ref><extra></extra></H1>
<H1><dentry>Palyam</dentry><dentryws></dentryws><Gram>napuM*</Gram><hmean no="1">PUla</hmean><hgram></hgram><ref></ref><extra></extra></H1>
<H1><dentry>PANiH</dentry><dentryws></dentryws><Gram>puM*</Gram><hmean no="1">sIrA,rAba</hmean><hgram></hgram><ref></ref><extra></extra></H1>
<H1><dentry>PANiwam</dentry><dentryws></dentryws><Gram>napuM*</Gram><hmean no="1">sIrA,rAba</hmean><hgram></hgram><ref></ref><extra></extra></H1>
<H1><dentry>PANta</dentry><dentryws></dentryws><Gram>vi*</Gram><hmean no="1">sugama prakriyA xvArA nirmiwa,AsAnI se banAyA huA</hmean><hgram></hgram><ref></ref><extra>jEse kADZA</extra></H1>
<H1><dentry>PANtaH</dentry><dentryws></dentryws><Gram>puM*</Gram><hmean no="1">arka,kADZA</hmean><hgram></hgram><ref>PANtamanAyAsasAXyaH kaRAyaviSeRaH  sixXA* ,PANtaciwrAswrapANayaH  Batti* 9/17,</ref><extra>xe0 BARya</extra></H1>
<H1><dentry>PANtam</dentry><dentryws></dentryws><Gram>napuM*</Gram><hmean no="1">arka,kADZA</hmean><hgram></hgram><ref>PANtamanAyAsasAXyaH kaRAyaviSeRaH  sixXA* ,PANtaciwrAswrapANayaH  Batti* 9/17,</ref><extra>xe0 BARya</extra></H1>
<H1><dentry>PAlaH</dentry><dentryws></dentryws><Gram>puM*</Gram><hmean no="1">hala kA Pala,PAlI</hmean><hgram></hgram><ref> manu* 6/16</ref><extra></extra><dentryws></dentryws><hmean no="2">bAloM kI mAMga nikAlanA,sImaMwaBAga</hmean><hgram></hgram><ref> nE* 1/16</ref><extra></extra></H1>
<H1><dentry>PAlam</dentry><dentryws></dentryws><Gram>napuM*</Gram><hmean no="1">hala kA Pala,PAlI</hmean><hgram></hgram><ref> manu* 6/16</ref><extra></extra><dentryws></dentryws><hmean no="2">bAloM kI mAMga nikAlanA,sImaMwaBAga</hmean><hgram></hgram><ref> nE* 1/16</ref><extra></extra>
<H2 entry="1"><dentry>PAlaH</dentry><dentryws></dentryws><Gram>puM*</Gram><hmean no="1">balarAma kA viSeRaNa</hmean><gender></gender><ref></ref><extra></extra><dentryws></dentryws><hmean no="2">Siva kA viSeRaNa</hmean><gender></gender><ref></ref><extra></extra><dentryws></dentryws><hmean no="3">nIbU kA pedZa</hmean><gender></gender><ref></ref><extra></extra></H2>
<H2 entry="4"><dentry>PAlam</dentry><dentryws></dentryws><Gram>napuM*</Gram><hmean no="1">sUwI kapadZA</hmean><gender></gender><ref></ref><extra></extra><dentryws></dentryws><hmean no="2">jowA huA Kewa</hmean><gender></gender><ref></ref><extra></extra></H2>
</H1>
<H1><dentry>PAlgunaH</dentry><dentryws></dentryws><Gram>puM*</Gram><hmean no="1">mahIne kA nAma</hmean><hgram></hgram><ref></ref><extra>jo ParavarI-mArca meM AwA hE</extra><dentryws></dentryws><hmean no="2">arjuna kA viSeRaNa mahA0meM nAma kI vyAKyA isa prakAra hE</hmean><hgram></hgram><ref>uwwarAByAM PalgunIByAM nakRawrAByAmahaM xivA,jAwo himavawaHpqRTe wena mAM PAlgunaM vixuH</ref><extra></extra><dentryws></dentryws><hmean no="3">vqkRa kA nAma,jise ?arjuna? kahawe hEM</hmean><hgram></hgram><ref></ref><extra></extra>
<H2 entry="1"><dentry>PAlgunAnujaH</dentry><dentryws></dentryws><Gram>puM*</Gram><hmean no="1">cEwra kA mahInA</hmean><gender></gender><ref></ref><extra></extra><dentryws></dentryws><hmean no="2">vasaMwakAla</hmean><gender></gender><ref></ref><extra></extra><dentryws></dentryws><hmean no="3">nakula Ora sahaxeva kA viSeRaNa</hmean><gender></gender><ref></ref><extra></extra></H2>
</H1>
<H1><dentry>PAlgunI</dentry><dentryws></dentryws><Gram>swrI*</Gram><hmean no="1">PAlguna mAsa kI pUrNimA</hmean><hgram></hgram><ref></ref><extra></extra>
<H2 entry="1"><dentry>PAlgunIBavaH</dentry><dentryws></dentryws><Gram>puM*</Gram><hmean no="1">vqhaspawi graha kA viSeRaNa</hmean><gender></gender><ref></ref><extra></extra></H2>
</H1>
<H1><dentry>PirafgaH</dentry><dentryws></dentryws><Gram>puM*</Gram><hmean no="1">PiraMgiyoM arWAw yUropiyanoM kA xeSa</hmean><hgram></hgram><ref></ref><extra></extra></H1>
<H1><dentry>Pirafgin</dentry><dentryws></dentryws><Gram>pUM*</Gram><hmean no="1">PiraMgI,aMgreja,yuropiyana</hmean><hgram></hgram><ref></ref><extra></extra></H1>
<H1><dentry>PukaH</dentry><dentryws></dentryws><Gram>puM*</Gram><hmean no="1">pakRI</hmean><hgram></hgram><ref></ref><extra></extra></H1>
<H1><dentry>Puw</dentry><dentryws></dentryws><Gram>avya*</Gram><hmean no="1">anukaraNamUlaka Sabxa jo prAyaH ?kq? ke sAWa prayukwa howA hE,warala paxArWoM meM PUMka mArane se pExA hone vAlI Xvani,kaBI-kaBI isase GqNA sUciwa howI hE</hmean><hgram></hgram><ref></ref><extra></extra></H1>
<H1><dentry>PUw</dentry><dentryws></dentryws><Gram>avya*</Gram><hmean no="1">anukaraNamUlaka Sabxa jo prAyaH ?kq? ke sAWa prayukwa howA hE,warala paxArWoM meM PUMka mArane se pExA hone vAlI Xvani,kaBI-kaBI isase GqNA sUciwa howI hE</hmean><hgram></hgram><ref></ref><extra></extra> <HP> reference elements <dentry>Puwkq</dentry><dentryws></dentryws><gram>vi*</gram><hmean>PUzka mAranA</hmean><gender></gender><ref>bAlaH pAyasaxagXo xaXyapi PUwkqwya BakRayawi  hi* 4/103</ref><extra></extra></HP> <HP> reference elements <dentry>PUwkq</dentry><dentryws></dentryws><gram>vi*</gram><hmean>PUzka mAranA</hmean><gender></gender><ref>bAlaH pAyasaxagXo xaXyapi PUwkqwya BakRayawi  hi* 4/103</ref><extra></extra></HP><H2 entry="0"><dentry>PuwkAraH</dentry><dentryws></dentryws><Gram>puM*</Gram><hmean no="1">PUzka mAranA</hmean><gender></gender><ref></ref><extra></extra><dentryws></dentryws><hmean no="2">sAzpa kI PuPakAra</hmean><gender></gender><ref></ref><extra></extra><dentryws></dentryws><hmean no="3">sI sI karanA,sAyaM sAyaM kI Xvani</hmean><gender></gender><ref></ref><extra></extra><dentryws></dentryws><hmean no="4">subakanA</hmean><gender></gender><ref></ref><extra></extra><dentryws></dentryws><hmean no="5">cIKa mAranA,jora kI cIKa,cIwkAra</hmean><gender></gender><ref></ref><extra></extra></H2>
<H2 entry="5"><dentry>PUwkAraH</dentry><dentryws></dentryws><Gram>puM*</Gram><hmean no="1">PUzka mAranA</hmean><gender></gender><ref></ref><extra></extra><dentryws></dentryws><hmean no="2">sAzpa kI PuPakAra</hmean><gender></gender><ref></ref><extra></extra><dentryws></dentryws><hmean no="3">sI sI karanA,sAyaM sAyaM kI Xvani</hmean><gender></gender><ref></ref><extra></extra><dentryws></dentryws><hmean no="4">subakanA</hmean><gender></gender><ref></ref><extra></extra><dentryws></dentryws><hmean no="5">cIKa mAranA,jora kI cIKa,cIwkAra</hmean><gender></gender><ref></ref><extra></extra></H2>
<H2 entry="10"><dentry>Puwkqwam</dentry><dentryws></dentryws><Gram>napuM*</Gram><hmean no="1">PUzka mAranA</hmean><gender></gender><ref></ref><extra></extra><dentryws></dentryws><hmean no="2">sAzpa kI PuPakAra</hmean><gender></gender><ref></ref><extra></extra><dentryws></dentryws><hmean no="3">sI sI karanA,sAyaM sAyaM kI Xvani</hmean><gender></gender><ref></ref><extra></extra><dentryws></dentryws><hmean no="4">subakanA</hmean><gender></gender><ref></ref><extra></extra><dentryws></dentryws><hmean no="5">cIKa mAranA,jora kI cIKa,cIwkAra</hmean><gender></gender><ref></ref><extra></extra></H2>
<H2 entry="15"><dentry>PUwkqwam</dentry><dentryws></dentryws><Gram>napuM*</Gram><hmean no="1">PUzka mAranA</hmean><gender></gender><ref></ref><extra></extra><dentryws></dentryws><hmean no="2">sAzpa kI PuPakAra</hmean><gender></gender><ref></ref><extra></extra><dentryws></dentryws><hmean no="3">sI sI karanA,sAyaM sAyaM kI Xvani</hmean><gender></gender><ref></ref><extra></extra><dentryws></dentryws><hmean no="4">subakanA</hmean><gender></gender><ref></ref><extra></extra><dentryws></dentryws><hmean no="5">cIKa mAranA,jora kI cIKa,cIwkAra</hmean><gender></gender><ref></ref><extra></extra></H2>
<H2 entry="20"><dentry>Puwkqwi</dentry><dentryws></dentryws><Gram>swrI*</Gram><hmean no="1">PUzka mAranA</hmean><gender></gender><ref></ref><extra></extra><dentryws></dentryws><hmean no="2">sAzpa kI PuPakAra</hmean><gender></gender><ref></ref><extra></extra><dentryws></dentryws><hmean no="3">sI sI karanA,sAyaM sAyaM kI Xvani</hmean><gender></gender><ref></ref><extra></extra><dentryws></dentryws><hmean no="4">subakanA</hmean><gender></gender><ref></ref><extra></extra><dentryws></dentryws><hmean no="5">cIKa mAranA,jora kI cIKa,cIwkAra</hmean><gender></gender><ref></ref><extra></extra></H2>
<H2 entry="25"><dentry>PUwkqwi</dentry><dentryws></dentryws><Gram>swrI*</Gram><hmean no="1">PUzka mAranA</hmean><gender></gender><ref></ref><extra></extra><dentryws></dentryws><hmean no="2">sAzpa kI PuPakAra</hmean><gender></gender><ref></ref><extra></extra><dentryws></dentryws><hmean no="3">sI sI karanA,sAyaM sAyaM kI Xvani</hmean><gender></gender><ref></ref><extra></extra><dentryws></dentryws><hmean no="4">subakanA</hmean><gender></gender><ref></ref><extra></extra><dentryws></dentryws><hmean no="5">cIKa mAranA,jora kI cIKa,cIwkAra</hmean><gender></gender><ref></ref><extra></extra></H2>
</H1>
<H1><dentry>PupPusaH</dentry><dentryws></dentryws><Gram>napuM*</Gram><hmean no="1">PePadZe</hmean><hgram></hgram><ref></ref><extra></extra></H1>
<H1><dentry>PupPusam</dentry><dentryws></dentryws><Gram>napuM*</Gram><hmean no="1">PePadZe</hmean><hgram></hgram><ref></ref><extra></extra></H1>
<H1><dentry>Pull</dentry><dentryws></dentryws><Gram>BvA*para*&lt;Pullawi&gt;&lt;Pulliwa&gt;</Gram><hmean no="1">kalI AnA,PUlanA,PulAnA,KilanA</hmean><hgram></hgram><ref></ref><extra>puRpa kA</extra></H1>
<H1><dentry>Pulla</dentry><dentryws></dentryws><Gram>BU* ka*kq*</Gram><hmean no="1">PElAyA huA,KilA huA,PUlA huA</hmean><hgram></hgram><ref>puRpaM ca PullaM navamallikAyAH prayAwi kAnwi pramaxAjanAnAm  qwu* 6/6,PullAraviMxavavaxanAm  cOra* 1</ref><extra></extra><dentryws></dentryws><hmean no="2">PUla AnA,KilA huA</hmean><hgram></hgram><ref> raGu* 9/63</ref><extra></extra><dentryws></dentryws><hmean no="3">viswAriwa,PElAyA huA,KUbaKulA huA</hmean><hgram></hgram><ref> paMca* 1/136</ref><extra>AzKoM kI BAzwi</extra>
<H2 entry="1"><dentry>Pullalocana</dentry><dentryws></dentryws><Gram>vi*</Gram><hmean no="1">KilI huI AzKoM vAlA</hmean><gender></gender><ref></ref><extra>harRa se</extra></H2>
<H2 entry="2"><dentry>PullalocanaH</dentry><dentryws></dentryws><Gram>puM*</Gram><hmean no="1">eka prakAra kA mqga</hmean><gender></gender><ref></ref><extra></extra></H2>
</H1>
<H1><dentry>PetkAraH</dentry><dentryws></dentryws><Gram>puM*</Gram><hmean no="1">cIKa,hUka</hmean><hgram></hgram><ref></ref><extra>kuwwe BedZiye kI Xvani</extra></H1>
<H1><dentry>PeNaH</dentry><dentryws></dentryws><Gram>puM*</Gram><hmean no="1">JAga,Pena</hmean><hgram></hgram><ref>gOrIvakwpraBrukutiracanA yA vihasyeva PenEH  meGa* 50,raGu* 13/11,manu* 2/61</ref><extra></extra><dentryws></dentryws><hmean no="2">muzha kA JAga yA bulabulA</hmean><hgram></hgram><ref></ref><extra></extra><dentryws></dentryws><hmean no="3">WUka</hmean><hgram></hgram><ref></ref><extra></extra></H1>
<H1><dentry>PenaH</dentry><dentryws></dentryws><Gram>puM*</Gram><hmean no="1">JAga,Pena</hmean><hgram></hgram><ref>gOrIvakwpraBrukutiracanA yA vihasyeva PenEH  meGa* 50,raGu* 13/11,manu* 2/61</ref><extra></extra><dentryws></dentryws><hmean no="2">muzha kA JAga yA bulabulA</hmean><hgram></hgram><ref></ref><extra></extra><dentryws></dentryws><hmean no="3">WUka</hmean><hgram></hgram><ref></ref><extra></extra>
<H2 entry="1"><dentry>PeNanapiNdaH</dentry><dentryws></dentryws><Gram>puM*</Gram><hmean no="1">bulabulA</hmean><gender></gender><ref></ref><extra></extra><dentryws></dentryws><hmean no="2">KoKalA vicAra,anaswiwva</hmean><gender></gender><ref></ref><extra></extra></H2>
<H2 entry="3"><dentry>PeNanavAhin</dentry><dentryws></dentryws><Gram>puM*</Gram><hmean no="1">CAnane ke kAma kA kapadZA</hmean><gender></gender><ref></ref><extra></extra></H2>
</H1>
<H1><dentry>PeNaka</dentry><dentryws></dentryws><Gram>vi*</Gram><hmean no="1"></hmean><hgram></hgram><ref></ref><extra>xe0? Pena?</extra></H1>
<H1><dentry>Penaka</dentry><dentryws></dentryws><Gram>vi*</Gram><hmean no="1"></hmean><hgram></hgram><ref></ref><extra>xe0? Pena?</extra></H1>
<H1><dentry>Penila</dentry><dentryws></dentryws><Gram>vi*</Gram><hmean no="1">JAgaxAra,bulabule vAlA,</hmean><hgram></hgram><ref>PenilamambUrASi  raGu* 13/2</ref><extra></extra></H1>
<H1><dentry>PeraH</dentry><dentryws></dentryws><Gram>puM*</Gram><hmean no="1">gIxadZa</hmean><hgram></hgram><ref></ref><extra></extra></H1>
<H1><dentry>PeraNdaH</dentry><dentryws></dentryws><Gram>puM*</Gram><hmean no="1">gIxadZa</hmean><hgram></hgram><ref></ref><extra></extra></H1>
<H1><dentry>PeravaH</dentry><dentryws></dentryws><Gram>puM*</Gram><hmean no="1">gIxadZa</hmean><hgram></hgram><ref>kranxawPeravacaNdadAwkqwi  mA* 5/19</ref><extra></extra><dentryws></dentryws><hmean no="2">XUrwa,baxamASa,Taga</hmean><hgram></hgram><ref></ref><extra></extra><dentryws></dentryws><hmean no="3">rAkRasa,piSAca</hmean><hgram></hgram><ref></ref><extra></extra></H1>
<H1><dentry>PeruH</dentry><dentryws></dentryws><Gram>puM*</Gram><hmean no="1">gIxadZa</hmean><hgram></hgram><ref></ref><extra></extra></H1>
<H1><dentry>Pelam</dentry><dentryws></dentryws><Gram>napuM*</Gram><hmean no="1">ucCiRta Bojana,Bojana kA vacA KucA BAga,jUTana</hmean><hgram></hgram><ref></ref><extra></extra></H1>
<H1><dentry>PelA</dentry><dentryws></dentryws><Gram>swrI*</Gram><hmean no="1">ucCiRta Bojana,Bojana kA vacA KucA BAga,jUTana</hmean><hgram></hgram><ref></ref><extra></extra></H1>
<H1><dentry>PelikA</dentry><dentryws></dentryws><Gram>swrI*</Gram><hmean no="1">ucCiRta Bojana,Bojana kA vacA KucA BAga,jUTana</hmean><hgram></hgram><ref></ref><extra></extra></H1>
<H1><dentry>PelI</dentry><dentryws></dentryws><Gram>swrI*</Gram><hmean no="1">ucCiRta Bojana,Bojana kA vacA KucA BAga,jUTana</hmean><hgram></hgram><ref></ref><extra></extra></H1>
<H1><dentry>PaNaBaraH</dentry><dentryws></dentryws><Gram>puM*</Gram><hmean no="1">sAzpa</hmean><hgram></hgram><ref></ref><extra></extra></H1>
<H1><dentry>PaNiwalpagaH</dentry><dentryws></dentryws><Gram>puM*</Gram><hmean no="1">viRNu kA viSeRaNa</hmean><hgram></hgram><ref></ref><extra></extra></H1>
<H1><dentry>PaNirjakaH</dentry><dentryws></dentryws><Gram>puM*</Gram><hmean no="1">wulasI kA eka Bexa, saPexa maravA</hmean><hgram></hgram><ref></ref><extra></extra></H1>
<H1><dentry>ParuNdaH</dentry><dentryws></dentryws><Gram>puM*</Gram><hmean no="1">harI pyAja</hmean><hgram></hgram><ref></ref><extra></extra></H1>
<H1><dentry>Palam</dentry><dentryws></dentryws><Gram>napuM*</Gram><hmean no="1">kRawipUrwi, prawipUrwi</hmean><hgram></hgram><ref></ref><extra></extra><dentryws></dentryws><hmean no="2">skanXAswi, aMsaPalaka</hmean><hgram></hgram><ref></ref><extra></extra><dentryws></dentryws><hmean no="3">upaja</hmean><hgram></hgram><ref></ref><extra></extra><dentryws></dentryws><hmean no="4">Pala</hmean><hgram></hgram><ref></ref><extra></extra><dentryws></dentryws><hmean no="5">pariNAma</hmean><hgram></hgram><ref></ref><extra></extra><dentryws></dentryws><hmean no="6">kqwya</hmean><hgram></hgram><ref></ref><extra></extra><dentryws></dentryws><hmean no="7">uxxeSya, prayojana</hmean><hgram></hgram><ref></ref><extra></extra><dentryws></dentryws><hmean no="8">upayoga, lABa</hmean><hgram></hgram><ref></ref><extra></extra><dentryws></dentryws><hmean no="9">sanwAna</hmean><hgram></hgram><ref></ref><extra></extra><dentryws></dentryws><hmean no="10">Palaka</hmean><hgram></hgram><ref></ref><extra>walavAra kA</extra><dentryws></dentryws><hmean no="11">wIra kI noka</hmean><hgram></hgram><ref></ref><extra></extra>
<H2 entry="1"><dentry>PalAXikAraH</dentry><dentryws></dentryws><Gram>puM*</Gram><hmean no="1">pariSrama kA xAvA</hmean><gender></gender><ref></ref><extra></extra></H2>
<H2 entry="2"><dentry>PalApUrvam</dentry><dentryws></dentryws><Gram>napuM*</Gram><hmean no="1">yajFa kA axqRta pariNAma</hmean><gender></gender><ref></ref><extra></extra></H2>
<H2 entry="3"><dentry>PalopayogaH</dentry><dentryws></dentryws><Gram>puM*</Gram><hmean no="1">Pala kA Ananxa lenA</hmean><gender></gender><ref></ref><extra></extra></H2>
<H2 entry="4"><dentry>PalagranWaH</dentry><dentryws></dentryws><Gram>puM*</Gram><hmean no="1">?grahoM kA mAnavakula para praBAva? viRayaka jyowiRa kA eka granWa</hmean><gender></gender><ref></ref><extra></extra></H2>
<H2 entry="5"><dentry>PalaBAvanA</dentry><dentryws></dentryws><Gram>swrI*</Gram><hmean no="1">pariNAma kA aXigrahaNa</hmean><gender></gender><ref></ref><extra></extra></H2>
<H2 entry="6"><dentry>PalaBuj</dentry><dentryws></dentryws><Gram>puM*</Gram><hmean no="1">banxara</hmean><gender></gender><ref></ref><extra></extra></H2>
<H2 entry="7"><dentry>PalamUlam</dentry><dentryws></dentryws><Gram>napuM*</Gram><hmean no="1">Pala Ora jadZeM</hmean><gender></gender><ref></ref><extra></extra></H2>
<H2 entry="8"><dentry>Palavarwwi</dentry><dentryws></dentryws><Gram>swrI*</Gram><hmean no="1">kapadZe kI banI bawwI jise cikanA karake anImA ke lie guxA meM raKA jAwA hEM</hmean><gender></gender><ref></ref><extra></extra></H2>
<H2 entry="9"><dentry>PalasWApanam</dentry><dentryws></dentryws><Gram>napuM*</Gram><hmean no="1">?sImanwonnayana? nAmaka saMskAra</hmean><gender></gender><ref></ref><extra></extra></H2>
</H1>
<H1><dentry>Palakam</dentry><dentryws></dentryws><Gram>napuM*</Gram><hmean no="1">waKwA, PattA</hmean><hgram></hgram><ref></ref><extra></extra><dentryws></dentryws><hmean no="2">tikiyA</hmean><hgram></hgram><ref></ref><extra></extra><dentryws></dentryws><hmean no="3">kUlhA</hmean><hgram></hgram><ref></ref><extra></extra><dentryws></dentryws><hmean no="4">hAWa kI haWelI</hmean><hgram></hgram><ref></ref><extra></extra><dentryws></dentryws><hmean no="5">lABa</hmean><hgram></hgram><ref></ref><extra></extra><dentryws></dentryws><hmean no="6">bANa kA muMha</hmean><hgram></hgram><ref></ref><extra></extra><dentryws></dentryws><hmean no="7">Arwava, qwusrAva</hmean><hgram></hgram><ref></ref><extra></extra><dentryws></dentryws><hmean no="8">lakadZI kA patadZA</hmean><hgram></hgram><ref></ref><extra></extra><dentryws></dentryws><hmean no="9">vqkRa kI CAla sana Axi</hmean><hgram></hgram><ref></ref><extra>kapadZe bunane ke lie</extra>
<H2 entry="1"><dentry>PalakapariXAnam</dentry><dentryws></dentryws><Gram>napuM*</Gram><hmean no="1">vaswroM ke rUpa meM  vqkRaCAla XAraNa karanA</hmean><gender></gender><ref></ref><extra></extra></H2>
</H1>
<H1><dentry>PaliH</dentry><dentryws></dentryws><Gram>puM*</Gram><hmean no="1">eka prakAra kI maCalI</hmean><hgram></hgram><ref></ref><extra></extra></H1>
<H1><dentry>PalguvAk</dentry><dentryws></dentryws><Gram>swrI*</Gram><hmean no="1">miWyApana, JUTApanA</hmean><hgram></hgram><ref></ref><extra></extra></H1>
<H1><dentry>PAlikA</dentry><dentryws></dentryws><Gram>swrI*</Gram><hmean no="1">grAsa, tukadZA</hmean><hgram></hgram><ref>mqxuvyaFjana,mAMsaPAlikAm   nE* 16/82</ref><extra></extra></H1>
<H1><dentry>PAlguneyaH</dentry><dentryws></dentryws><Gram>puM*</Gram><hmean no="1">arjuna kA puwra, aBimanyu</hmean><hgram></hgram><ref></ref><extra></extra></H1>
<H1><dentry>PitsUwram</dentry><dentryws></dentryws><Gram>napuM*</Gram><hmean no="1">vyAkaraNa kA eka granWa jisake racayiwA SAnwanAvAcArya We</hmean><hgram></hgram><ref></ref><extra></extra></H1>
<H1><dentry>PuttikA</dentry><dentryws></dentryws><Gram>swrI*</Gram><hmean no="1">eka prakAra kA bunA huA kapadZA</hmean><hgram></hgram><ref></ref><extra></extra></H1>
<H1><dentry>PuwkqwiH</dentry><dentryws></dentryws><Gram>swrI*</Gram><hmean no="1">PUzka mAranA, sIsI Sabxa karanA</hmean><hgram></hgram><ref></ref><extra></extra></H1>
<H1><dentry>Pulifga</dentry><dentryws></dentryws><Gram>puM*</Gram><hmean no="1">upaxaMSa, garmI kA roga</hmean><hgram></hgram><ref></ref><extra></extra></H1>
<H1><dentry>Pullavaxana</dentry><dentryws></dentryws><Gram>vi*,ba*sa*</Gram><hmean no="1">prasannamuKa, KuSa xiKAI xene vAlA</hmean><hgram></hgram><ref></ref><extra></extra></H1>
<H1><dentry>PeFjakaH</dentry><dentryws></dentryws><Gram>puM*</Gram><hmean no="1">eka prakAra kA pakRI</hmean><hgram></hgram><ref></ref><extra></extra></H1>
<H1><dentry>PenaXarman</dentry><dentryws></dentryws><Gram>vi*</Gram><hmean no="1">kRaNaBaMgura, kRaNasWAyI, bulabule kI BAMwi, asWira</hmean><hgram></hgram><ref> mahA* 3/35/2</ref><extra></extra></H1>
<H1><dentry>PenAyiwam</dentry><dentryws></dentryws><Gram>napuM*,nA*XA*</Gram><hmean no="1">muKa ke pArSvavarwI BAga se kI gaI hAWI kI kadZakayukwa garjana, ciMGAdZa</hmean><hgram></hgram><ref> mAwa* 2/13</ref><extra></extra></H1>
</dicti>